setup.py
tdaemon.py
tdaemon.egg-info/PKG-INFO
tdaemon.egg-info/SOURCES.txt
tdaemon.egg-info/dependency_links.txt
tdaemon.egg-info/entry_points.txt
tdaemon.egg-info/top_level.txt