Metadata-Version: 1.0
Name: tdaemon
Version: 0.1.1
Summary: Test Daemon
Home-page: http://github.com/brunobord/tdaemon
Author: John Paulett
Author-email: john@7oars.com
License: MIT
Keywords: test,testing,noestests,django,py.test
Platform: POSIX
Platform: Windows
Classifier: License :: OSI Approved :: MIT License
Classifier: Topic :: Software Development :: Testing
Classifier: Programming Language :: Python
Classifier: Intended Audience :: Developers
